veriport_dashboard
