Metadata-Version: 1.1
Name: veriport-dashboard
Version: 0.5.2
Summary: This is a dashboard utility made specifically for Veriport project
Home-page: https://github.com/verifydx/veriport-dashboard
Author: Ronil Rufo
Author-email: ronil.rufo@gmail.com
License: UNKNOWN
Download-URL: https://github.com/verifydx/veriport-dashboard/tarball/0.1
Keywords: veriport,dashboard,veriport_dashboard
Platform: UNKNOWN
